   [
   {
        "name": "murciélago",
        "ATK": 5,
        "HP": 35,
        "DEF": 1,
        "HabilityI": {
            "name": "vampirismoI",
            "vampirismI": true,
            "%": 25
        },
        "habilityII": false,
        "habilityIII": false
    },
    {
        "name": "slime",
        "ATK": 4,
        "HP": 60,
        "DEF": 2,
        "habilityI": false,
        "habilityII": false,
        "habilityIII": false
    },
    {
        "name": "Esqueleto",
        "ATK": 2,
        "HP": 100,
        "DEF": 4,
        "habilityI": false,
        "habilityII": false,
        "habilityIII": false
    }
]